{"name":"Service-Autocomplete","className":"DataModel","filePaths":["default.project.json"],"children":[{"name":"ServerStorage","className":"ServerStorage","children":[{"name":"Auto Completion","className":"Folder","children":[{"name":"Source","className":"Script","filePaths":["Plugin\\init.server.lua"],"children":[{"name":"lexer","className":"ModuleScript","filePaths":["Plugin\\lexer\\init.lua"],"children":[{"name":"language","className":"ModuleScript","filePaths":["Plugin\\lexer\\language.lua"]}]}]}]}]}]}